{
	"type": "input",
	"convention": "long-lat",
	"useCase": "trip",
	"optimOption": "default",
	"carModel": "Tesla cybertruck",
	"maxAutonomy": 200,
	"currentAutonomy": 50,
	"subscription": "",
	"userSteps": [
		{
			"location": [
				5.928,
				43.124228
			],
			"name": "Toulon",
			"address": ""
		},
		{
			"location": [
				5.36978,
				43.296482
			],
			"name": "Marseille",
			"address": ""
		},
		{
			"location": [
				4.83566,
				45.76404
			],
			"name": "Lyon",
			"address": ""
		},
		{
			"location": [
				5.05015,
				47.34083
			],
			"name": "Dijon",
			"address": ""
		},
		{
			"location": [
				2.3499,
				48.85661
			],
			"name": "Paris",
			"address": ""
		}
	]
}
