{
	"cars": [
		{
			"model": "Renault ZOE R135",
			"subscription": "",
			"maxAutonomy": 390,
			"currentAutonomy": 390,
			"capacity": 52,
			"courantConnecteurs": [
				{
					"courant": "AC (Three-Phase)",
					"connecteur": "IEC 62196-2 Type 2",
					"puissance": 22
				},
				{
					"courant": "DC",
					"connecteur": "IEC 62196-3 Configuration FF",
					"puissance": 50
				}
			]
		},
		{
			"model": "Renault Twizy 80",
			"subscription": "",
			"maxAutonomy": 81,
			"currentAutonomy": 81,
			"capacity": 6.1,
			"courantConnecteurs": [
				{
					"courant": "AC (Single-Phase)",
					"connecteur": "None",
					"puissance": 3.7
				}
			]
		}
	]
}
